{
	code: "clothes",
	class: "ItemWearable",
	variantgroups: [
		{ code: "category",  states: ["butterflypin"] },
		{ code: "emblem", states: [
			"acadianhairstreak", "alchemical", "bandedpeacock", "bluekallima", "bluemorpho", "bluepansy", "bogcopper", "bronzecopper", "cabbagewhite", "clipper", "coloradohairstreak", "comma", "commonbrimstone", "darkbluepansy", "desertorangetip", "easterntigerswallowtail", "godartsnumberwing", "goldbandedforester", "greatpurplehairstreak", "greencharaxes", "largewhite", "littlemetalmark", "littlewoodsatyr", "malachite", "marbledwhite", "milbertstortoiseshell", "mourningcloak", "oakblue", "paintedbeauty", "pallidnawab", "peacock", "pipevineswallowtail", "purpleemperor", "redadmiral", "redglider", "redpostman", "resplendantforester", "ringlet", "rot", "rust", "rustytippedpage", "silveryblue", "smallheath", "speckledwood", "temporal", "whiteadmiral", "whitepeacock", "zebraheliconan", "zebraswallowtail", "zeredaskipper"
		] },
	],
	shapeByType: {
		"*": {
			base: "entity/humanoid/seraph/clothing/emblem/butterflypins/{emblem}" 
		}
	},
	texturesByType: {
		"*": {
			"seraph": { base: "block/transparent" }
		},
	},
	storageFlags: 128,
	attributesByType: {
		"*": {
			wearableAttachment: true,
			clothescategory: "emblem",
			warmth: 0
		}
	},	
	creativeinventory: { "general": ["*"], "items": ["*"], "clothing": ["*"] },
	renderAlphaTest: 0.25,
	fpHandTransformByType: {
		"*": {
			translation: { x: 0.6, y: 0, z: -0.5 },
			rotation: { x: 180, y: 42, z: -29 },
			scale: 2.5
		}
	},
	tpHandTransformByType: {
		"*": {
		translation: { x: -0.35, y: -0.8, z: -0.8 },
		rotation: { x: 0, y: 0, z: -111 },
		scale: 0.55
		}
	},
	guiTransformByType: {
		"*": {
			rotate: false,
			translation: { x: 0, y: 0, z: 0 },
			rotation: { x: 174, y: -119, z: -22 },
			origin: { x: 0.4, y: 1.33, z: 0.55 },
			scale: 3.31
		}
	},
	groundTransformByType: {
		"*": {
			translation: { x: 0.05, y: -0.3, z: 0 },
			rotation: { x: 0, y: 0, z: 0 },
			scale: 2
		}
	}
}