{
	code: "meta",
	classByType: {
		"*-spawner": "BlockSpawner"
	},
	entityClassByType: {
		"*-spawner": "Spawner",
		"*-music": "MusicTrigger"
	},
	attributes: {
		handbook: {
			exclude: true
		},
		canChiselByType: {
			"*-collider": true
		}
	},
	variantgroups: [
		{ code:"type", states: ["filler", "pathway", "underground", "spawner", "collider", "music", "blocklayer"] },
	],
	shape: { base: "block/basic/cube" },
	drawtype: "cube",
	creativeinventory: { "meta": ["*"] },
	drops: [],
	blockmaterial: "Meta",
	faceCullMode: "Merge",
	vertexFlags: {
		zOffset: 7
	},
	renderPass: "meta",
	replaceable: 900,
	lightAbsorption: 0,
	textures: {
		all: { base: "block/meta/{type}" }
	},
	resistance: 0.25,
	sideopaque: {
		all: false
	},
	sidesolid: {
		all: false
	},
	collisionboxByType: {
		"*-collider": { x1: 0, y1: 0, z1: 0, x2: 1, y2: 1, z2: 1 },
		"*": null,
	}
}