{"GameVersion":"1.19.0","SizeX":3,"SizeY":4,"SizeZ":3,"BlockCodes":{"1856":"game:meta-underground","1798":"game:planks-aged-ns","1032":"game:chest-east"},"ItemCodes":{"506":"game:lootrandomizer","267":"game:blade-falx-iron","574":"game:spear-generic-granite","3595":"game:stackrandomizer-jonasframes"},"Indices":[2098176,1025,1048577,1049601,2097153,2098177,2099201,3146753,1048578,1049602,2098178],"BlockIds":[1856,1856,1798,1798,1798,1032,1856,1856,1856,1798,1798],"DecorIndices":[],"DecorIds":[],"BlockEntities":{"2098177":"!<d@[F*O[J\"98H*E,TfC\"onW'!<d@[F*b$R\"98T3@VfsmCI<#NAI;p\\ATMrFARTY%\"po!]G%GQ5DfU+(#'\"^#Dfg%+!!!!'\"`nKuFE7Zf0E;+R!!)ir!!!$\"!!!$&F('6'!<<*\"\"pT-j@:O(,#6f0j@:O'Q!<<*\"$NU5-!<<*\"!!EL9BOPdgAH2^$63%2oF*(i#CG?%tF*(i#CB+A8!!#1a!!!$\"!!!!%#%M=TDI[5X!(]EV!!`NZ!!*'\"!\"08:!!*'\"!!E[ODffE(6YKnG@q>W?J3Er5!!NdCDfS0\\De!QMDe*Dd@q]FpF=h'4F*%QgFEqh:$=e!jCgh:(ARmS\"$#O6pBL-NKCh3SH!!!!"},"Entities":[],"ReplaceMode":2,"EntranceRotation":-1}